CHANGES.txt
LICENSE.txt
MANIFEST.in
README.txt
setup.cfg
setup.py
Sillyfacter.egg-info/SOURCES.txt
bin/sillyfacter
sillyfacter/__init__.py
sillyfacter/common.py
sillyfacter/filesystem.py
sillyfacter/network.py
sillyfacter/os.py
sillyfacter/process.py
sillyfacter/user.py
sillyfacter.egg-info/PKG-INFO
sillyfacter.egg-info/SOURCES.txt
sillyfacter.egg-info/dependency_links.txt
sillyfacter.egg-info/entry_points.txt
sillyfacter.egg-info/not-zip-safe
sillyfacter.egg-info/requires.txt
sillyfacter.egg-info/top_level.txt
sillyfacter/customs/__init__.py
sillyfacter/output/__init__.py
sillyfacter/output/json.py