Metadata-Version: 1.0
Name: Sillyfacter
Version: 0.3.0.4
Summary: Sillyfacter prints JSON facts related to the state of the system. The state here means process running on the host, their open connections and files. Also users logged in, mount points on the host etcetra. These information is useful in mapping out dependencies.
Home-page: https://github.com/hihellobolke/Sillyfacter
Author: Gautam R Singh
Author-email: g@ut.am
License: Apache
Keywords: facter json process lsof mounts facts host os state
Platform: UNKNOWN
